hourglass_tensorflow/__init__.py
hourglass_tensorflow/handlers/__init__.py
hourglass_tensorflow/handlers/_transformation.py
hourglass_tensorflow/handlers/data.py
hourglass_tensorflow/handlers/dataset.py
hourglass_tensorflow/handlers/engines.py
hourglass_tensorflow/handlers/meta.py
hourglass_tensorflow/handlers/model.py
hourglass_tensorflow/handlers/train.py
hourglass_tensorflow/layers/__init__.py
hourglass_tensorflow/layers/batch_norm_relu_conv.py
hourglass_tensorflow/layers/conv_batch_norm_relu.py
hourglass_tensorflow/layers/conv_block.py
hourglass_tensorflow/layers/downsampling.py
hourglass_tensorflow/layers/hourglass.py
hourglass_tensorflow/layers/residual.py
hourglass_tensorflow/layers/skip.py
hourglass_tensorflow/losses/__init__.py
hourglass_tensorflow/losses/sigmoid_cross_entropy.py
hourglass_tensorflow/metrics/__init__.py
hourglass_tensorflow/metrics/correct_keypoints.py
hourglass_tensorflow/metrics/distance.py
hourglass_tensorflow/models/__init__.py
hourglass_tensorflow/models/hourglass.py
hourglass_tensorflow/types/__init__.py
hourglass_tensorflow/types/config/__init__.py
hourglass_tensorflow/types/config/data.py
hourglass_tensorflow/types/config/dataset.py
hourglass_tensorflow/types/config/fields.py
hourglass_tensorflow/types/config/metadata.py
hourglass_tensorflow/types/config/model.py
hourglass_tensorflow/types/config/train.py
hourglass_tensorflow/types/htf_data_types.py
hourglass_tensorflow/utils/__init__.py
hourglass_tensorflow/utils/_errors.py
hourglass_tensorflow/utils/object_logger.py
hourglass_tensorflow/utils/parsers/__init__.py
hourglass_tensorflow/utils/parsers/_parse_import.py
hourglass_tensorflow/utils/parsers/htf.py
hourglass_tensorflow/utils/parsers/mpii.py
hourglass_tensorflow/utils/plots.py
hourglass_tensorflow/utils/sets/__init__.py
hourglass_tensorflow/utils/tf.py
hourglass_tensorflow/utils/writers.py
hourglass_tensorflow-1.0.1.dist-info/entry_points.txt
hourglass_tensorflow-1.0.1.dist-info/WHEEL
hourglass_tensorflow-1.0.1.dist-info/METADATA
hourglass_tensorflow-1.0.1.dist-info/RECORD
